LICENSE.txt
MANIFEST.in
README.rst
_version.py
setup.cfg
setup.py
versioneer.py
include/rank_filter.hxx
rank_filter.egg-info/PKG-INFO
rank_filter.egg-info/SOURCES.txt
rank_filter.egg-info/dependency_links.txt
rank_filter.egg-info/not-zip-safe
rank_filter.egg-info/requires.txt
rank_filter.egg-info/top_level.txt
src/rank_filter.pxd
src/rank_filter.pyx
tests/__init__.py
tests/test_rank_filter.py