Metadata-Version: 1.1
Name: rank-filter
Version: 0.5.0
Summary: A simple python module containing an in-place linear rank filter optimized in C++.
Home-page: https://github.com/nanshe-org/rank_filter
Author: John Kirkham
Author-email: kirkhamj@janelia.hhmi.org
License: BSD
Download-URL: https://github.com/nanshe-org/rank_filter/archive/v0.5.0.tar.gz
Platform: UNKNOWN
Classifier: Development Status :: 5 - Production/Stable
Classifier: Intended Audience :: Developers
Classifier: Intended Audience :: Science/Research
Classifier: License :: OSI Approved :: BSD License
Classifier: Operating System :: POSIX :: Linux
Classifier: Operating System :: MacOS :: MacOS X
Classifier: Operating System :: Microsoft :: Windows
Classifier: Programming Language :: C++
Classifier: Programming Language :: Cython
Classifier: Programming Language :: Python
Classifier: Programming Language :: Python :: 2.7
Classifier: Programming Language :: Python :: 3.5
Classifier: Programming Language :: Python :: 3.6
Classifier: Topic :: Scientific/Engineering
Classifier: Topic :: Software Development :: Libraries
